LICENSE
MANIFEST.in
README.rst
setup.py
readability/__init__.py
readability/auth.py
readability/clients.py
readability/core.py
readability/utils.py
readability_api.egg-info/PKG-INFO
readability_api.egg-info/SOURCES.txt
readability_api.egg-info/dependency_links.txt
readability_api.egg-info/requires.txt
readability_api.egg-info/top_level.txt