Metadata-Version: 1.1
Name: readability-api
Version: 1.0.2
Summary: Python client for the Readability Reader and Parser APIs.
Home-page: https://github.com/arc90/python-readability-api
Author: The Readability Team
Author-email: philip@readability.com
License: MIT
Platform: UNKNOWN
Classifier: Development Status :: 5 - Production/Stable
Classifier: Intended Audience :: Developers
Classifier: Natural Language :: English
Classifier: License :: OSI Approved :: MIT License
Classifier: Programming Language :: Python
Classifier: Programming Language :: Python :: 2.7
Classifier: Programming Language :: Python :: 3.5
Classifier: Programming Language :: Python :: Implementation :: PyPy
